PyexQE/__init__.py
PyexQE/inputFile.py
PyexQE/model.py
PyexQE-0.0.1.dist-info/METADATA
PyexQE-0.0.1.dist-info/WHEEL
PyexQE-0.0.1.dist-info/top_level.txt
PyexQE-0.0.1.dist-info/RECORD
